{
    "key": "group_5ddfada4c3ffe",
    "title": "News Posts",
    "fields": [
        {
            "key": "field_5ddfadad14750",
            "label": "Post content",
            "name": "post_content",
            "type": "flexible_content",
            "instructions": "",
            "required": 0,
            "conditional_logic": 0,
            "wrapper": {
                "width": "",
                "class": "",
                "id": ""
            },
            "button_label": "Add Row",
            "min": "",
            "max": "",
            "layouts": [
                {
                    "key": "5ddfadb79926b",
                    "name": "content_block",
                    "label": "Content block",
                    "display": "row",
                    "sub_fields": [
                        {
                            "key": "field_5ddfae8e14757",
                            "label": "Content",
                            "name": "content",
                            "type": "wysiwyg",
                            "instructions": "",
                            "required": 0,
                            "conditional_logic": 0,
                            "wrapper": {
                                "width": "",
                                "class": "",
                                "id": ""
                            },
                            "default_value": "",
                            "tabs": "all",
                            "toolbar": "full",
                            "media_upload": 1,
                            "delay": 0
                        }
                    ],
                    "min": "",
                    "max": ""
                },
                {
                    "key": "5de0d89342f42",
                    "name": "video_block",
                    "label": "Video Block",
                    "display": "row",
                    "sub_fields": [
                        {
                            "key": "field_5de0d89342f43",
                            "label": "Vimeo ID",
                            "name": "vimeo",
                            "type": "text",
                            "instructions": "",
                            "required": 0,
                            "conditional_logic": 0,
                            "wrapper": {
                                "width": 100,
                                "class": "",
                                "id": ""
                            },
                            "default_value": "",
                            "placeholder": "",
                            "prepend": "",
                            "append": "",
                            "maxlength": "",
                            "readonly": 0,
                            "disabled": 0
                        },
                        {
                            "key": "field_5de0db56c3f05",
                            "label": "Youtube ID",
                            "name": "youtube",
                            "type": "text",
                            "instructions": "",
                            "required": 0,
                            "conditional_logic": 0,
                            "wrapper": {
                                "width": "",
                                "class": "",
                                "id": ""
                            },
                            "default_value": "",
                            "placeholder": "",
                            "prepend": "",
                            "append": "",
                            "maxlength": "",
                            "readonly": 0,
                            "disabled": 0
                        }
                    ],
                    "min": "",
                    "max": ""
                },
                {
                    "key": "5ddfaea214758",
                    "name": "gallery",
                    "label": "Gallery",
                    "display": "row",
                    "sub_fields": [
                        {
                            "key": "field_5ddfaeab1475a",
                            "label": "Layout",
                            "name": "layout",
                            "type": "select",
                            "instructions": "",
                            "required": 0,
                            "conditional_logic": 0,
                            "wrapper": {
                                "width": "",
                                "class": "",
                                "id": ""
                            },
                            "choices": {
                                "1": "2x2 | 2x1, 2x1",
                                "2": "2x1, 2x1 | 2x2",
                                "3 1x1, 1x1": "3 1x1, 1x1"
                            },
                            "default_value": [],
                            "allow_null": 0,
                            "multiple": 0,
                            "ui": 0,
                            "ajax": 0,
                            "placeholder": "",
                            "disabled": 0,
                            "readonly": 0,
                            "return_format": "value"
                        },
                        {
                            "key": "field_5ddfaece1475b",
                            "label": "Images",
                            "name": "images",
                            "type": "gallery",
                            "instructions": "",
                            "required": 1,
                            "conditional_logic": 0,
                            "wrapper": {
                                "width": "",
                                "class": "",
                                "id": ""
                            },
                            "min": "",
                            "max": "",
                            "preview_size": "thumbnail",
                            "library": "all",
                            "min_width": "",
                            "min_height": "",
                            "min_size": "",
                            "max_width": "",
                            "max_height": "",
                            "max_size": "",
                            "mime_types": "",
                            "return_format": "array",
                            "insert": "append"
                        },
                        {
                            "key": "field_5de0ca8ae4765",
                            "label": "Add padding",
                            "name": "padding",
                            "type": "true_false",
                            "instructions": "",
                            "required": 0,
                            "conditional_logic": 0,
                            "wrapper": {
                                "width": "",
                                "class": "",
                                "id": ""
                            },
                            "message": "",
                            "default_value": 0,
                            "ui": 0,
                            "ui_on_text": "",
                            "ui_off_text": ""
                        },
                        {
                            "key": "field_5de0caa1e4766",
                            "label": "No padding bottom",
                            "name": "no_padding_bottom",
                            "type": "true_false",
                            "instructions": "",
                            "required": 0,
                            "conditional_logic": 0,
                            "wrapper": {
                                "width": "",
                                "class": "",
                                "id": ""
                            },
                            "message": "",
                            "default_value": 0,
                            "ui": 0,
                            "ui_on_text": "",
                            "ui_off_text": ""
                        }
                    ],
                    "min": "",
                    "max": ""
                }
            ]
        }
    ],
    "location": [
        [
            {
                "param": "post_type",
                "operator": "==",
                "value": "post"
            }
        ]
    ],
    "menu_order": 0,
    "position": "normal",
    "style": "default",
    "label_placement": "top",
    "instruction_placement": "label",
    "hide_on_screen": "",
    "active": 1,
    "description": "",
    "modified": 1709843707
}